hyper2web/__init__.py
hyper2web/abstract.py
hyper2web/app.py
hyper2web/cli.py
hyper2web/exceptions.py
hyper2web/http.py
hyper2web/router.py
hyper2web/server.py
hyper2web/sslsocket.py
hyper2web-0.0.4.dist-info/DESCRIPTION.rst
hyper2web-0.0.4.dist-info/METADATA
hyper2web-0.0.4.dist-info/RECORD
hyper2web-0.0.4.dist-info/WHEEL
hyper2web-0.0.4.dist-info/entry_points.txt
hyper2web-0.0.4.dist-info/metadata.json
hyper2web-0.0.4.dist-info/top_level.txt
