Metadata-Version: 2.0
Name: hyper2web
Version: 0.0.4
Summary: Coroutine based H2 Web backend framework built for the future.
Home-page: https://github.com/CreatCodeBuild/hyper2web
Author: Xuanzhe Wang
Author-email: wangxuanzhealbert@gmail.com
License: UNKNOWN
Keywords: hyper2web
Platform: UNKNOWN
Classifier: Development Status :: 2 - Pre-Alpha
Classifier: Intended Audience :: Developers
Classifier: Natural Language :: English
Classifier: Programming Language :: Python :: 3.5
Classifier: Programming Language :: Python :: 3.6
Requires-Dist: Click (>=6.0)
Requires-Dist: curio
Requires-Dist: h2
